Metadata-Version: 2.1
Name: clickhouse_driver_fork_0_2_4
Version: 0.0.2
Summary: Fix of the version 0.2.4, for the clickhouse's version 22.3
Author-email: Carlos Yago <carlosfyago@gmail.com>
Maintainer-email: Carlos Yago <carlosfyago@gmail.com>
License: This is the MIT license: http://www.opensource.org/licenses/mit-license.php
Classifier: License :: OSI Approved :: MIT License
Classifier: Operating System :: OS Independent
Classifier: Programming Language :: Python :: 3
Requires-Python: >=3.7
